Metadata-Version: 1.1
Name: logs-check-plugin
Version: 1.2.0
Summary: check for logs in a log file
Home-page: https://github.com/pablodav/gurobi_machines_plugin
Author: Pablo Estigarribia
Author-email: pablodav@gmail.com
License: MIT
Platform: UNKNOWN
Classifier: Development Status :: 5 - Production/Stable
Classifier: Intended Audience :: System Administrators
Classifier: License :: OSI Approved :: MIT License
Classifier: Programming Language :: Python :: 3
Classifier: Programming Language :: Python :: 3 :: Only
Classifier: Topic :: System :: Monitoring
